onerecord/__init__.py
onerecord/client.py
onerecord/exceptions.py
onerecord/utils.py
onerecord/models/__init__.py
onerecord/models/api.py
onerecord/models/cargo.py
onerecord/models/enums.py
onerecord-0.2.0.dist-info/METADATA
onerecord-0.2.0.dist-info/WHEEL
onerecord-0.2.0.dist-info/licenses/LICENSE.md
onerecord-0.2.0.dist-info/RECORD
