Metadata-Version: 2.1
Name: onerecord
Version: 0.2.0
Summary: ONE Record with Python
Project-URL: Homepage, https://github.com/ddoeppner/one-record-python
Project-URL: Bug Tracker, https://github.com/ddoeppner/one-record-python/issues
Author-email: "Daniel A. Doeppner" <daniel@leetly.com>
License-File: LICENSE.md
Classifier: Intended Audience :: Developers
Classifier: Intended Audience :: Information Technology
Classifier: Intended Audience :: Other Audience
Classifier: Intended Audience :: Science/Research
Classifier: License :: OSI Approved :: MIT License
Classifier: Operating System :: OS Independent
Classifier: Programming Language :: Python
Classifier: Programming Language :: Python :: 3 :: Only
Classifier: Programming Language :: Python :: 3.9
Classifier: Programming Language :: Python :: 3.10
Classifier: Programming Language :: Python :: 3.11
Classifier: Topic :: Software Development
Classifier: Topic :: Software Development :: Libraries
Classifier: Topic :: Software Development :: Libraries :: Application Frameworks
Classifier: Topic :: Software Development :: Libraries :: Python Modules
Requires-Python: >=3.9
Requires-Dist: pydantic>=1.10.2
Requires-Dist: requests>=2.28.1
